{
  "$schema": "https://developer.microsoft.com/json-schemas/spfx-build/package-solution.schema.json",
  "solution": {
    "name": "sharepoint-11-client-side-solution",
    "id": "bc84616c-7bce-4b7f-8c84-66ba42d5c02b",
    "version": "1.0.0.0",
    "includeClientSideAssets": true,
    "skipFeatureDeployment": true,
    "isDomainIsolated": false,
    "developer": {
      "name": "",
      "websiteUrl": "",
      "privacyUrl": "",
      "termsOfUseUrl": "",
      "mpnId": "Undefined-1.20.0"
    },
    "metadata": {
      "shortDescription": {
        "default": "sharepoint-11 description"
      },
      "longDescription": {
        "default": "sharepoint-11 description"
      },
      "screenshotPaths": [],
      "videoUrl": "",
      "categories": []
    },
    "features": [
      {
        "title": "sharepoint-11 Feature",
        "description": "The feature that activates elements of the sharepoint-11 solution.",
        "id": "1baa9233-d14c-4d76-8011-0f283f9afaad",
        "version": "1.0.0.0"
      }
    ]
  },
  "paths": {
    "zippedPackage": "solution/sharepoint-11.sppkg"
  }
}
